{"commitInfo":{"timestamp":1777393045444,"operation":"UPDATE","operationParameters":{"predicate":"[\"(id_corrida#10553 = 101)\"]"},"readVersion":5,"isolationLevel":"Serializable","isBlindAppend":false,"operationMetrics":{"numRemovedFiles":"3","numRemovedBytes":"5441","numCopiedRows":"0","numDeletionVectorsAdded":"0","numDeletionVectorsRemoved":"0","numAddedChangeFiles":"0","executionTimeMs":"3034","numDeletionVectorsUpdated":"0","scanTimeMs":"2707","numAddedFiles":"3","numUpdatedRows":"3","numAddedBytes":"5427","rewriteTimeMs":"326"},"engineInfo":"Apache-Spark/3.5.1 Delta-Lake/3.2.0","txnId":"b4510207-2959-47b6-bdc9-da95db66fbe5"}}
{"add":{"path":"part-00000-482d78fb-0e36-4e28-bbc1-15fcc6826f5b-c000.snappy.parquet","partitionValues":{},"size":1809,"modificationTime":1777393045427,"dataChange":true,"stats":"{\"numRecords\":1,\"minValues\":{\"id_corrida\":101,\"id_motorista\":1,\"origem\":\"Centro\",\"destino\":\"Aeroporto\",\"valor_corrida\":50.0,\"status_corrida\":\"Finalizada\"},\"maxValues\":{\"id_corrida\":101,\"id_motorista\":1,\"origem\":\"Centro\",\"destino\":\"Aeroporto\",\"valor_corrida\":50.0,\"status_corrida\":\"Finalizada\"},\"nullCount\":{\"id_corrida\":0,\"id_motorista\":0,\"origem\":0,\"destino\":0,\"valor_corrida\":0,\"status_corrida\":0}}"}}
{"add":{"path":"part-00001-2aeacd09-b68e-4809-8335-97564c5eff21-c000.snappy.parquet","partitionValues":{},"size":1809,"modificationTime":1777393045427,"dataChange":true,"stats":"{\"numRecords\":1,\"minValues\":{\"id_corrida\":101,\"id_motorista\":1,\"origem\":\"Centro\",\"destino\":\"Aeroporto\",\"valor_corrida\":50.0,\"status_corrida\":\"Finalizada\"},\"maxValues\":{\"id_corrida\":101,\"id_motorista\":1,\"origem\":\"Centro\",\"destino\":\"Aeroporto\",\"valor_corrida\":50.0,\"status_corrida\":\"Finalizada\"},\"nullCount\":{\"id_corrida\":0,\"id_motorista\":0,\"origem\":0,\"destino\":0,\"valor_corrida\":0,\"status_corrida\":0}}"}}
{"add":{"path":"part-00002-3aee2ccc-8039-40a7-8969-7df88120914f-c000.snappy.parquet","partitionValues":{},"size":1809,"modificationTime":1777393045427,"dataChange":true,"stats":"{\"numRecords\":1,\"minValues\":{\"id_corrida\":101,\"id_motorista\":1,\"origem\":\"Centro\",\"destino\":\"Aeroporto\",\"valor_corrida\":50.0,\"status_corrida\":\"Finalizada\"},\"maxValues\":{\"id_corrida\":101,\"id_motorista\":1,\"origem\":\"Centro\",\"destino\":\"Aeroporto\",\"valor_corrida\":50.0,\"status_corrida\":\"Finalizada\"},\"nullCount\":{\"id_corrida\":0,\"id_motorista\":0,\"origem\":0,\"destino\":0,\"valor_corrida\":0,\"status_corrida\":0}}"}}
{"remove":{"path":"part-00000-3fe5c0d7-fd84-4d1e-9a19-97fd861cb8c0-c000.snappy.parquet","deletionTimestamp":1777393045443,"dataChange":true,"extendedFileMetadata":true,"partitionValues":{},"size":1823}}
{"remove":{"path":"part-00000-eff2bd70-7db3-4dad-ab55-9368d5048200-c000.snappy.parquet","deletionTimestamp":1777393045443,"dataChange":true,"extendedFileMetadata":true,"partitionValues":{},"size":1809}}
{"remove":{"path":"part-00001-a0149101-54ef-45a9-b726-a1c94e401f18-c000.snappy.parquet","deletionTimestamp":1777393045443,"dataChange":true,"extendedFileMetadata":true,"partitionValues":{},"size":1809}}
